locust_telc/__init__.py
locust_telc/__main__.py
locust_telc/_version.py
locust_telc/argument_parser.py
locust_telc/clients.py
locust_telc/debug.py
locust_telc/dispatch.py
locust_telc/env.py
locust_telc/event.py
locust_telc/exception.py
locust_telc/html.py
locust_telc/input_events.py
locust_telc/log.py
locust_telc/main.py
locust_telc/py.typed
locust_telc/runners.py
locust_telc/shape.py
locust_telc/stats.py
locust_telc/web.py
locust_telc/contrib/__init__.py
locust_telc/contrib/fasthttp.py
locust_telc/rpc/__init__.py
locust_telc/rpc/protocol.py
locust_telc/rpc/zmqrpc.py
locust_telc/test/__init__.py
locust_telc/test/fake_module1_for_env_test.py
locust_telc/test/fake_module2_for_env_test.py
locust_telc/test/mock_locustfile.py
locust_telc/test/mock_logging.py
locust_telc/test/test_debugging.py
locust_telc/test/test_dispatch.py
locust_telc/test/test_env.py
locust_telc/test/test_fasthttp.py
locust_telc/test/test_http.py
locust_telc/test/test_interruptable_task.py
locust_telc/test/test_load_locustfile.py
locust_telc/test/test_locust_class.py
locust_telc/test/test_log.py
locust_telc/test/test_main.py
locust_telc/test/test_old_wait_api.py
locust_telc/test/test_parser.py
locust_telc/test/test_runners.py
locust_telc/test/test_sequential_taskset.py
locust_telc/test/test_stats.py
locust_telc/test/test_tags.py
locust_telc/test/test_taskratio.py
locust_telc/test/test_users.py
locust_telc/test/test_util.py
locust_telc/test/test_wait_time.py
locust_telc/test/test_web.py
locust_telc/test/test_zmqrpc.py
locust_telc/test/testcases.py
locust_telc/test/util.py
locust_telc/user/__init__.py
locust_telc/user/inspectuser.py
locust_telc/user/sequential_taskset.py
locust_telc/user/task.py
locust_telc/user/users.py
locust_telc/user/wait_time.py
locust_telc/util/__init__.py
locust_telc/util/cache.py
locust_telc/util/deprecation.py
locust_telc/util/exception_handler.py
locust_telc/util/load_locustfile.py
locust_telc/util/rounding.py
locust_telc/util/timespan.py
locust_telc/webui/dist/auth.html
locust_telc-1.4.dist-info/LICENSE
locust_telc-1.4.dist-info/METADATA
locust_telc-1.4.dist-info/WHEEL
locust_telc-1.4.dist-info/entry_points.txt
locust_telc-1.4.dist-info/top_level.txt
locust_telc-1.4.dist-info/zip-safe
locust_telc-1.4.dist-info/RECORD
